{
	"CommonAllPlayers": [
		{
			"person_id": 203919,
			"display_last_comma_first": "Adams, Jordan",
			"display_first_last": "Jordan Adams",
			"rosterstatus": 1,
			"from_year": "2014",
			"to_year": "2015",
			"playercode": "Jordan_Adams",
			"team_id": 1610612763,
			"team_city": "Memphis",
			"team_name": "Grizzlies",
			"team_abbreviation": "MEM",
			"team_code": "grizzlies",
			"games_played_flag": "Y"
		},
		{
			"person_id": 1626146,
			"display_last_comma_first": "Alexander, Cliff",
			"display_first_last": "Cliff Alexander",
			"rosterstatus": 1,
			"from_year": "2015",
			"to_year": "2015",
			"playercode": "cliff_alexander",
			"team_id": 1610612757,
			"team_city": "Portland",
			"team_name": "Trail Blazers",
			"team_abbreviation": "POR",
			"team_code": "blazers",
			"games_played_flag": "Y"
		},
		{
			"person_id": 200811,
			"display_last_comma_first": "Amundson, Lou",
			"display_first_last": "Lou Amundson",
			"rosterstatus": 1,
			"from_year": "2006",
			"to_year": "2015",
			"playercode": "lou_amundson",
			"team_id": 1610612752,
			"team_city": "New York",
			"team_name": "Knicks",
			"team_abbreviation": "NYK",
			"team_code": "knicks",
			"games_played_flag": "Y"
		},
		{
			"person_id": 202341,
			"display_last_comma_first": "Anderson, James",
			"display_first_last": "James Anderson",
			"rosterstatus": 1,
			"from_year": "2010",
			"to_year": "2015",
			"playercode": "james_anderson",
			"team_id": 1610612758,
			"team_city": "Sacramento",
			"team_name": "Kings",
			"team_abbreviation": "SAC",
			"team_code": "kings",
			"games_played_flag": "Y"
		},
		{
			"person_id": 203648,
			"display_last_comma_first": "Antetokounmpo, Thanasis",
			"display_first_last": "Thanasis Antetokounmpo",
			"rosterstatus": 0,
			"from_year": "2015",
			"to_year": "2015",
			"playercode": "thanasis_antetokounmpo",
			"team_id": 0,
			"team_city": "",
			"team_name": "",
			"team_abbreviation": "",
			"team_code": "",
			"games_played_flag": "Y"
		},
		{
			"person_id": 201202,
			"display_last_comma_first": "Anthony, Joel",
			"display_first_last": "Joel Anthony",
			"rosterstatus": 1,
			"from_year": "2007",
			"to_year": "2015",
			"playercode": "joel_anthony",
			"team_id": 1610612765,
			"team_city": "Detroit",
			"team_name": "Pistons",
			"team_abbreviation": "DET",
			"team_code": "pistons",
			"games_played_flag": "Y"
		},
		{
			"person_id": 203951,
			"display_last_comma_first": "Appling, Keith",
			"display_first_last": "Keith Appling",
			"rosterstatus": 0,
			"from_year": "2015",
			"to_year": "2015",
			"playercode": "keith_appling",
			"team_id": 0,
			"team_city": "",
			"team_name": "",
			"team_abbreviation": "",
			"team_code": "",
			"games_played_flag": "Y"
		},
		{
			"person_id": 201965,
			"display_last_comma_first": "Ayres, Jeff",
			"display_first_last": "Jeff Ayres",
			"rosterstatus": 1,
			"from_year": "2009",
			"to_year": "2015",
			"playercode": "jeff_ayres",
			"team_id": 1610612746,
			"team_city": "LA",
			"team_name": "Clippers",
			"team_abbreviation": "LAC",
			"team_code": "clippers",
			"games_played_flag": "Y"
		},
		{
			"person_id": 203946,
			"display_last_comma_first": "Bairstow, Cameron",
			"display_first_last": "Cameron Bairstow",
			"rosterstatus": 1,
			"from_year": "2014",
			"to_year": "2015",
			"playercode": "cameron_bairstow",
			"team_id": 1610612741,
			"team_city": "Chicago",
			"team_name": "Bulls",
			"team_abbreviation": "CHI",
			"team_code": "bulls",
			"games_played_flag": "Y"
		},
		{
			"person_id": 203946,
			"display_last_comma_first": "Bairstow, Cameron",
			"display_first_last": "Cameron Bairstow",
			"rosterstatus": 1,
			"from_year": "2014",
			"to_year": "2015",
			"playercode": "cameron_bairstow",
			"team_id": 1610612765,
			"team_city": "Detroit",
			"team_name": "Pistons",
			"team_abbreviation": "DET",
			"team_code": "pistons",
			"games_played_flag": "Y"
		},
		{
			"person_id": 200745,
			"display_last_comma_first": "Bargnani, Andrea",
			"display_first_last": "Andrea Bargnani",
			"rosterstatus": 0,
			"from_year": "2006",
			"to_year": "2015",
			"playercode": "andrea_bargnani",
			"team_id": 0,
			"team_city": "",
			"team_name": "",
			"team_abbreviation": "",
			"team_code": "",
			"games_played_flag": "Y"
		},
		{
			"person_id": 201573,
			"display_last_comma_first": "Bayless, Jerryd",
			"display_first_last": "Jerryd Bayless",
			"rosterstatus": 1,
			"from_year": "2008",
			"to_year": "2016",
			"playercode": "jerryd_bayless",
			"team_id": 1610612749,
			"team_city": "Milwaukee",
			"team_name": "Bucks",
			"team_abbreviation": "MIL",
			"team_code": "bucks",
			"games_played_flag": "Y"
		},
		{
			"person_id": 201976,
			"display_last_comma_first": "Beverley, Patrick",
			"display_first_last": "Patrick Beverley",
			"rosterstatus": 1,
			"from_year": "2012",
			"to_year": "2016",
			"playercode": "patrick_beverley",
			"team_id": 1610612745,
			"team_city": "Houston",
			"team_name": "Rockets",
			"team_abbreviation": "HOU",
			"team_code": "rockets",
			"games_played_flag": "Y"
		},
		{
			"person_id": 201971,
			"display_last_comma_first": "Blair, DeJuan",
			"display_first_last": "DeJuan Blair",
			"rosterstatus": 0,
			"from_year": "2009",
			"to_year": "2015",
			"playercode": "dejuan_blair",
			"team_id": 0,
			"team_city": "",
			"team_name": "",
			"team_abbreviation": "",
			"team_code": "",
			"games_played_flag": "Y"
		},
		{
			"person_id": 2581,
			"display_last_comma_first": "Blake, Steve",
			"display_first_last": "Steve Blake",
			"rosterstatus": 1,
			"from_year": "2003",
			"to_year": "2015",
			"playercode": "steve_blake",
			"team_id": 1610612765,
			"team_city": "Detroit",
			"team_name": "Pistons",
			"team_abbreviation": "DET",
			"team_code": "pistons",
			"games_played_flag": "Y"
		},
		{
			"person_id": 2588,
			"display_last_comma_first": "Bonner, Matt",
			"display_first_last": "Matt Bonner",
			"rosterstatus": 1,
			"from_year": "2004",
			"to_year": "2015",
			"playercode": "matt_bonner",
			"team_id": 1610612759,
			"team_city": "San Antonio",
			"team_name": "Spurs",
			"team_abbreviation": "SAS",
			"team_code": "spurs",
			"games_played_flag": "Y"
		},
		{
			"person_id": 2547,
			"display_last_comma_first": "Bosh, Chris",
			"display_first_last": "Chris Bosh",
			"rosterstatus": 1,
			"from_year": "2003",
			"to_year": "2016",
			"playercode": "Chris_Bosh",
			"team_id": 1610612748,
			"team_city": "Miami",
			"team_name": "Heat",
			"team_abbreviation": "MIA",
			"team_code": "heat",
			"games_played_flag": "Y"
		},
		{
			"person_id": 1882,
			"display_last_comma_first": "Brand, Elton",
			"display_first_last": "Elton Brand",
			"rosterstatus": 1,
			"from_year": "1999",
			"to_year": "2015",
			"playercode": "elton_brand",
			"team_id": 1610612755,
			"team_city": "Philadelphia",
			"team_name": "76ers",
			"team_abbreviation": "PHI",
			"team_code": "sixers",
			"games_played_flag": "Y"
		},
		{
			"person_id": 1626148,
			"display_last_comma_first": "Brown, Anthony",
			"display_first_last": "Anthony Brown",
			"rosterstatus": 1,
			"from_year": "2015",
			"to_year": "2015",
			"playercode": "anthony_brown",
			"team_id": 1610612747,
			"team_city": "Los Angeles",
			"team_name": "Lakers",
			"team_abbreviation": "LAL",
			"team_code": "lakers",
			"games_played_flag": "Y"
		},
		{
			"person_id": 203485,
			"display_last_comma_first": "Brown, Lorenzo",
			"display_first_last": "Lorenzo Brown",
			"rosterstatus": 1,
			"from_year": "2013",
			"to_year": "2015",
			"playercode": "lorenzo_brown",
			"team_id": 1610612765,
			"team_city": "Detroit",
			"team_name": "Pistons",
			"team_abbreviation": "DET",
			"team_code": "pistons",
			"games_played_flag": "Y"
		},
		{
			"person_id": 203900,
			"display_last_comma_first": "Brown, Markel",
			"display_first_last": "Markel Brown",
			"rosterstatus": 1,
			"from_year": "2014",
			"to_year": "2015",
			"playercode": "markel_brown",
			"team_id": 1610612751,
			"team_city": "Brooklyn",
			"team_name": "Nets",
			"team_abbreviation": "BKN",
			"team_code": "nets",
			"games_played_flag": "Y"
		},
		{
			"person_id": 977,
			"display_last_comma_first": "Bryant, Kobe",
			"display_first_last": "Kobe Bryant",
			"rosterstatus": 1,
			"from_year": "1996",
			"to_year": "2015",
			"playercode": "kobe_bryant",
			"team_id": 1610612747,
			"team_city": "Los Angeles",
			"team_name": "Lakers",
			"team_abbreviation": "LAL",
			"team_code": "lakers",
			"games_played_flag": "Y"
		},
		{
			"person_id": 201978,
			"display_last_comma_first": "Budinger, Chase",
			"display_first_last": "Chase Budinger",
			"rosterstatus": 1,
			"from_year": "2009",
			"to_year": "2015",
			"playercode": "chase_budinger",
			"team_id": 1610612756,
			"team_city": "Phoenix",
			"team_name": "Suns",
			"team_abbreviation": "PHX",
			"team_code": "suns",
			"games_played_flag": "Y"
		},
		{
			"person_id": 203493,
			"display_last_comma_first": "Bullock, Reggie",
			"display_first_last": "Reggie Bullock",
			"rosterstatus": 1,
			"from_year": "2013",
			"to_year": "2016",
			"playercode": "reggie_bullock",
			"team_id": 1610612765,
			"team_city": "Detroit",
			"team_name": "Pistons",
			"team_abbreviation": "DET",
			"team_code": "pistons",
			"games_played_flag": "Y"
		},
		{
			"person_id": 202692,
			"display_last_comma_first": "Burks, Alec",
			"display_first_last": "Alec Burks",
			"rosterstatus": 1,
			"from_year": "2011",
			"to_year": "2016",
			"playercode": "Alec_Burks",
			"team_id": 1610612762,
			"team_city": "Utah",
			"team_name": "Jazz",
			"team_abbreviation": "UTA",
			"team_code": "jazz",
			"games_played_flag": "Y"
		},
		{
			"person_id": 2406,
			"display_last_comma_first": "Butler, Caron",
			"display_first_last": "Caron Butler",
			"rosterstatus": 1,
			"from_year": "2002",
			"to_year": "2015",
			"playercode": "caron_butler",
			"team_id": 1610612758,
			"team_city": "Sacramento",
			"team_name": "Kings",
			"team_abbreviation": "SAC",
			"team_code": "kings",
			"games_played_flag": "Y"
		},
		{
			"person_id": 2446,
			"display_last_comma_first": "Butler, Rasual",
			"display_first_last": "Rasual Butler",
			"rosterstatus": 0,
			"from_year": "2002",
			"to_year": "2015",
			"playercode": "rasual_butler",
			"team_id": 0,
			"team_city": "",
			"team_name": "",
			"team_abbreviation": "",
			"team_code": "",
			"games_played_flag": "Y"
		},
		{
			"person_id": 203998,
			"display_last_comma_first": "Caboclo, Bruno",
			"display_first_last": "Bruno Caboclo",
			"rosterstatus": 1,
			"from_year": "2014",
			"to_year": "2016",
			"playercode": "bruno_caboclo",
			"team_id": 1610612761,
			"team_city": "Toronto",
			"team_name": "Raptors",
			"team_abbreviation": "TOR",
			"team_code": "raptors",
			"games_played_flag": "Y"
		},
		{
			"person_id": 201596,
			"display_last_comma_first": "Chalmers, Mario",
			"display_first_last": "Mario Chalmers",
			"rosterstatus": 0,
			"from_year": "2008",
			"to_year": "2015",
			"playercode": "mario_chalmers",
			"team_id": 0,
			"team_city": "",
			"team_name": "",
			"team_abbreviation": "",
			"team_code": "",
			"games_played_flag": "Y"
		},
		{
			"person_id": 1626262,
			"display_last_comma_first": "Clarke, Coty",
			"display_first_last": "Coty Clarke",
			"rosterstatus": 0,
			"from_year": "2015",
			"to_year": "2015",
			"playercode": "coty_clarke",
			"team_id": 0,
			"team_city": "",
			"team_name": "",
			"team_abbreviation": "",
			"team_code": "",
			"games_played_flag": "Y"
		},
		{
			"person_id": 202708,
			"display_last_comma_first": "Cole, Norris",
			"display_first_last": "Norris Cole",
			"rosterstatus": 1,
			"from_year": "2011",
			"to_year": "2015",
			"playercode": "norris_cole",
			"team_id": 1610612740,
			"team_city": "New Orleans",
			"team_name": "Pelicans",
			"team_abbreviation": "NOP",
			"team_code": "pelicans",
			"games_played_flag": "Y"
		},
		{
			"person_id": 203142,
			"display_last_comma_first": "Copeland, Chris",
			"display_first_last": "Chris Copeland",
			"rosterstatus": 0,
			"from_year": "2012",
			"to_year": "2015",
			"playercode": "chris_copeland",
			"team_id": 0,
			"team_city": "",
			"team_name": "",
			"team_abbreviation": "",
			"team_code": "",
			"games_played_flag": "Y"
		},
		{
			"person_id": 203955,
			"display_last_comma_first": "Cotton, Bryce",
			"display_first_last": "Bryce Cotton",
			"rosterstatus": 1,
			"from_year": "2014",
			"to_year": "2015",
			"playercode": "Bryce_Cotton",
			"team_id": 1610612763,
			"team_city": "Memphis",
			"team_name": "Grizzlies",
			"team_abbreviation": "MEM",
			"team_code": "grizzlies",
			"games_played_flag": "Y"
		},
		{
			"person_id": 203099,
			"display_last_comma_first": "Cunningham, Jared",
			"display_first_last": "Jared Cunningham",
			"rosterstatus": 0,
			"from_year": "2012",
			"to_year": "2015",
			"playercode": "jared_cunningham",
			"team_id": 0,
			"team_city": "",
			"team_name": "",
			"team_abbreviation": "",
			"team_code": "",
			"games_played_flag": "Y"
		},
		{
			"person_id": 1626183,
			"display_last_comma_first": "Dawson, Branden",
			"display_first_last": "Branden Dawson",
			"rosterstatus": 1,
			"from_year": "2015",
			"to_year": "2015",
			"playercode": "Branden_Dawson",
			"team_id": 1610612746,
			"team_city": "LA",
			"team_name": "Clippers",
			"team_abbreviation": "LAC",
			"team_code": "clippers",
			"games_played_flag": "Y"
		},
		{
			"person_id": 1626214,
			"display_last_comma_first": "Dejean-Jones, Bryce",
			"display_first_last": "Bryce Dejean-Jones",
			"rosterstatus": 0,
			"from_year": "2015",
			"to_year": "2015",
			"playercode": "bryce_dejean-jones",
			"team_id": 0,
			"team_city": "",
			"team_name": "",
			"team_abbreviation": "",
			"team_code": "",
			"games_played_flag": "Y"
		},
		{
			"person_id": 203915,
			"display_last_comma_first": "Dinwiddie, Spencer",
			"display_first_last": "Spencer Dinwiddie",
			"rosterstatus": 1,
			"from_year": "2014",
			"to_year": "2015",
			"playercode": "Spencer_Dinwiddie",
			"team_id": 1610612765,
			"team_city": "Detroit",
			"team_name": "Pistons",
			"team_abbreviation": "DET",
			"team_code": "pistons",
			"games_played_flag": "Y"
		},
		{
			"person_id": 203915,
			"display_last_comma_first": "Dinwiddie, Spencer",
			"display_first_last": "Spencer Dinwiddie",
			"rosterstatus": 1,
			"from_year": "2014",
			"to_year": "2015",
			"playercode": "Spencer_Dinwiddie",
			"team_id": 1610612741,
			"team_city": "Chicago",
			"team_name": "Bulls",
			"team_abbreviation": "CHI",
			"team_code": "bulls",
			"games_played_flag": "Y"
		},
		{
			"person_id": 201962,
			"display_last_comma_first": "Douglas, Toney",
			"display_first_last": "Toney Douglas",
			"rosterstatus": 1,
			"from_year": "2009",
			"to_year": "2015",
			"playercode": "toney_douglas",
			"team_id": 1610612740,
			"team_city": "New Orleans",
			"team_name": "Pelicans",
			"team_abbreviation": "NOP",
			"team_code": "pelicans",
			"games_played_flag": "Y"
		},
		{
			"person_id": 1626251,
			"display_last_comma_first": "Dukan, Duje",
			"display_first_last": "Duje Dukan",
			"rosterstatus": 1,
			"from_year": "2015",
			"to_year": "2015",
			"playercode": "duje_dukan",
			"team_id": 1610612758,
			"team_city": "Sacramento",
			"team_name": "Kings",
			"team_abbreviation": "SAC",
			"team_code": "kings",
			"games_played_flag": "Y"
		},
		{
			"person_id": 1495,
			"display_last_comma_first": "Duncan, Tim",
			"display_first_last": "Tim Duncan",
			"rosterstatus": 1,
			"from_year": "1997",
			"to_year": "2015",
			"playercode": "tim_duncan",
			"team_id": 1610612759,
			"team_city": "San Antonio",
			"team_name": "Spurs",
			"team_abbreviation": "SAS",
			"team_code": "spurs",
			"games_played_flag": "Y"
		},
		{
			"person_id": 203921,
			"display_last_comma_first": "Early, Cleanthony",
			"display_first_last": "Cleanthony Early",
			"rosterstatus": 1,
			"from_year": "2014",
			"to_year": "2015",
			"playercode": "Cleanthony_Early",
			"team_id": 1610612752,
			"team_city": "New York",
			"team_name": "Knicks",
			"team_abbreviation": "NYK",
			"team_code": "knicks",
			"games_played_flag": "Y"
		},
		{
			"person_id": 204067,
			"display_last_comma_first": "Eddie, Jarell",
			"display_first_last": "Jarell Eddie",
			"rosterstatus": 1,
			"from_year": "2015",
			"to_year": "2015",
			"playercode": "Jarell_Eddie",
			"team_id": 1610612764,
			"team_city": "Washington",
			"team_name": "Wizards",
			"team_abbreviation": "WAS",
			"team_code": "wizards",
			"games_played_flag": "Y"
		},
		{
			"person_id": 201961,
			"display_last_comma_first": "Ellington, Wayne",
			"display_first_last": "Wayne Ellington",
			"rosterstatus": 1,
			"from_year": "2009",
			"to_year": "2016",
			"playercode": "wayne_ellington",
			"team_id": 1610612751,
			"team_city": "Brooklyn",
			"team_name": "Nets",
			"team_abbreviation": "BKN",
			"team_code": "nets",
			"games_played_flag": "Y"
		},
		{
			"person_id": 202379,
			"display_last_comma_first": "Evans, Jeremy",
			"display_first_last": "Jeremy Evans",
			"rosterstatus": 1,
			"from_year": "2010",
			"to_year": "2015",
			"playercode": "Jeremy_Evans",
			"team_id": 1610612742,
			"team_city": "Dallas",
			"team_name": "Mavericks",
			"team_abbreviation": "DAL",
			"team_code": "mavericks",
			"games_played_flag": "Y"
		},
		{
			"person_id": 201936,
			"display_last_comma_first": "Evans, Tyreke",
			"display_first_last": "Tyreke Evans",
			"rosterstatus": 1,
			"from_year": "2009",
			"to_year": "2016",
			"playercode": "tyreke_evans",
			"team_id": 1610612740,
			"team_city": "New Orleans",
			"team_name": "Pelicans",
			"team_abbreviation": "NOP",
			"team_code": "pelicans",
			"games_played_flag": "Y"
		},
		{
			"person_id": 203105,
			"display_last_comma_first": "Ezeli, Festus",
			"display_first_last": "Festus Ezeli",
			"rosterstatus": 1,
			"from_year": "2012",
			"to_year": "2016",
			"playercode": "Festus_Ezeli",
			"team_id": 1610612744,
			"team_city": "Golden State",
			"team_name": "Warriors",
			"team_abbreviation": "GSW",
			"team_code": "warriors",
			"games_played_flag": "Y"
		},
		{
			"person_id": 200770,
			"display_last_comma_first": "Farmar, Jordan",
			"display_first_last": "Jordan Farmar",
			"rosterstatus": 1,
			"from_year": "2006",
			"to_year": "2016",
			"playercode": "jordan_farmar",
			"team_id": 1610612763,
			"team_city": "Memphis",
			"team_name": "Grizzlies",
			"team_abbreviation": "MEM",
			"team_code": "grizzlies",
			"games_played_flag": "Y"
		},
		{
			"person_id": 202690,
			"display_last_comma_first": "Fredette, Jimmer",
			"display_first_last": "Jimmer Fredette",
			"rosterstatus": 0,
			"from_year": "2011",
			"to_year": "2015",
			"playercode": "jimmer_fredette",
			"team_id": 0,
			"team_city": "",
			"team_name": "",
			"team_abbreviation": "",
			"team_code": "",
			"games_played_flag": "Y"
		},
		{
			"person_id": 708,
			"display_last_comma_first": "Garnett, Kevin",
			"display_first_last": "Kevin Garnett",
			"rosterstatus": 1,
			"from_year": "1995",
			"to_year": "2015",
			"playercode": "Kevin_Garnett",
			"team_id": 1610612750,
			"team_city": "Minnesota",
			"team_name": "Timberwolves",
			"team_abbreviation": "MIN",
			"team_code": "timberwolves",
			"games_played_flag": "Y"
		},
		{
			"person_id": 202087,
			"display_last_comma_first": "Gee, Alonzo",
			"display_first_last": "Alonzo Gee",
			"rosterstatus": 1,
			"from_year": "2009",
			"to_year": "2015",
			"playercode": "Alonzo_Gee",
			"team_id": 1610612740,
			"team_city": "New Orleans",
			"team_name": "Pelicans",
			"team_abbreviation": "NOP",
			"team_code": "pelicans",
			"games_played_flag": "Y"
		},
		{
			"person_id": 2400,
			"display_last_comma_first": "Gooden, Drew",
			"display_first_last": "Drew Gooden",
			"rosterstatus": 1,
			"from_year": "2002",
			"to_year": "2015",
			"playercode": "drew_gooden",
			"team_id": 1610612764,
			"team_city": "Washington",
			"team_name": "Wizards",
			"team_abbreviation": "WAS",
			"team_code": "wizards",
			"games_played_flag": "Y"
		},
		{
			"person_id": 202726,
			"display_last_comma_first": "Goudelock, Andrew",
			"display_first_last": "Andrew Goudelock",
			"rosterstatus": 1,
			"from_year": "2011",
			"to_year": "2015",
			"playercode": "andrew_goudelock",
			"team_id": 1610612745,
			"team_city": "Houston",
			"team_name": "Rockets",
			"team_abbreviation": "HOU",
			"team_code": "rockets",
			"games_played_flag": "Y"
		},
		{
			"person_id": 203475,
			"display_last_comma_first": "Green, Erick",
			"display_first_last": "Erick Green",
			"rosterstatus": 0,
			"from_year": "2014",
			"to_year": "2015",
			"playercode": "erick_green",
			"team_id": 0,
			"team_city": "",
			"team_name": "",
			"team_abbreviation": "",
			"team_code": "",
			"games_played_flag": "Y"
		},
		{
			"person_id": 203268,
			"display_last_comma_first": "Gutierrez, Jorge",
			"display_first_last": "Jorge Gutierrez",
			"rosterstatus": 1,
			"from_year": "2013",
			"to_year": "2015",
			"playercode": "jorge_gutierrez",
			"team_id": 1610612766,
			"team_city": "Charlotte",
			"team_name": "Hornets",
			"team_abbreviation": "CHA",
			"team_code": "hornets",
			"games_played_flag": "Y"
		},
		{
			"person_id": 203798,
			"display_last_comma_first": "Hairston, PJ",
			"display_first_last": "PJ Hairston",
			"rosterstatus": 1,
			"from_year": "2014",
			"to_year": "2015",
			"playercode": "PJ_Hairston",
			"team_id": 1610612763,
			"team_city": "Memphis",
			"team_name": "Grizzlies",
			"team_abbreviation": "MEM",
			"team_code": "grizzlies",
			"games_played_flag": "Y"
		},
		{
			"person_id": 202706,
			"display_last_comma_first": "Hamilton, Jordan",
			"display_first_last": "Jordan Hamilton",
			"rosterstatus": 1,
			"from_year": "2011",
			"to_year": "2015",
			"playercode": "jordan_hamilton",
			"team_id": 1610612740,
			"team_city": "New Orleans",
			"team_name": "Pelicans",
			"team_abbreviation": "NOP",
			"team_code": "pelicans",
			"games_played_flag": "Y"
		},
		{
			"person_id": 201946,
			"display_last_comma_first": "Hansbrough, Tyler",
			"display_first_last": "Tyler Hansbrough",
			"rosterstatus": 1,
			"from_year": "2009",
			"to_year": "2015",
			"playercode": "tyler_hansbrough",
			"team_id": 1610612766,
			"team_city": "Charlotte",
			"team_name": "Hornets",
			"team_abbreviation": "CHA",
			"team_code": "hornets",
			"games_played_flag": "Y"
		},
		{
			"person_id": 202712,
			"display_last_comma_first": "Harper, Justin",
			"display_first_last": "Justin Harper",
			"rosterstatus": 0,
			"from_year": "2011",
			"to_year": "2015",
			"playercode": "Justin_Harper",
			"team_id": 0,
			"team_city": "",
			"team_name": "",
			"team_abbreviation": "",
			"team_code": "",
			"games_played_flag": "Y"
		},
		{
			"person_id": 2734,
			"display_last_comma_first": "Harris, Devin",
			"display_first_last": "Devin Harris",
			"rosterstatus": 1,
			"from_year": "2004",
			"to_year": "2016",
			"playercode": "devin_harris",
			"team_id": 1610612742,
			"team_city": "Dallas",
			"team_name": "Mavericks",
			"team_abbreviation": "DAL",
			"team_code": "mavericks",
			"games_played_flag": "Y"
		},
		{
			"person_id": 101236,
			"display_last_comma_first": "Hayes, Charles",
			"display_first_last": "Charles Hayes",
			"rosterstatus": 0,
			"from_year": "2005",
			"to_year": "2015",
			"playercode": "chuck_hayes",
			"team_id": 0,
			"team_city": "",
			"team_name": "",
			"team_abbreviation": "",
			"team_code": "",
			"games_played_flag": "Y"
		},
		{
			"person_id": 201581,
			"display_last_comma_first": "Hickson, JJ",
			"display_first_last": "JJ Hickson",
			"rosterstatus": 1,
			"from_year": "2008",
			"to_year": "2015",
			"playercode": "jj_hickson",
			"team_id": 1610612764,
			"team_city": "Washington",
			"team_name": "Wizards",
			"team_abbreviation": "WAS",
			"team_code": "wizards",
			"games_played_flag": "Y"
		},
		{
			"person_id": 2550,
			"display_last_comma_first": "Hinrich, Kirk",
			"display_first_last": "Kirk Hinrich",
			"rosterstatus": 1,
			"from_year": "2003",
			"to_year": "2015",
			"playercode": "kirk_hinrich",
			"team_id": 1610612737,
			"team_city": "Atlanta",
			"team_name": "Hawks",
			"team_abbreviation": "ATL",
			"team_code": "hawks",
			"games_played_flag": "Y"
		},
		{
			"person_id": 201950,
			"display_last_comma_first": "Holiday, Jrue",
			"display_first_last": "Jrue Holiday",
			"rosterstatus": 1,
			"from_year": "2009",
			"to_year": "2016",
			"playercode": "jrue_holiday",
			"team_id": 1610612740,
			"team_city": "New Orleans",
			"team_name": "Pelicans",
			"team_abbreviation": "NOP",
			"team_code": "pelicans",
			"games_played_flag": "Y"
		},
		{
			"person_id": 204066,
			"display_last_comma_first": "Holland, John",
			"display_first_last": "John Holland",
			"rosterstatus": 1,
			"from_year": "2015",
			"to_year": "2015",
			"playercode": "john_holland",
			"team_id": 1610612738,
			"team_city": "Boston",
			"team_name": "Celtics",
			"team_abbreviation": "BOS",
			"team_code": "celtics",
			"games_played_flag": "Y"
		},
		{
			"person_id": 200797,
			"display_last_comma_first": "Hollins, Ryan",
			"display_first_last": "Ryan Hollins",
			"rosterstatus": 0,
			"from_year": "2006",
			"to_year": "2015",
			"playercode": "ryan_hollins",
			"team_id": 0,
			"team_city": "",
			"team_name": "",
			"team_abbreviation": "",
			"team_code": "",
			"games_played_flag": "Y"
		},
		{
			"person_id": 203962,
			"display_last_comma_first": "Huestis, Josh",
			"display_first_last": "Josh Huestis",
			"rosterstatus": 1,
			"from_year": "2015",
			"to_year": "2016",
			"playercode": "josh_huestis",
			"team_id": 1610612760,
			"team_city": "Oklahoma City",
			"team_name": "Thunder",
			"team_abbreviation": "OKC",
			"team_code": "thunder",
			"games_played_flag": "Y"
		},
		{
			"person_id": 1626154,
			"display_last_comma_first": "Hunter, RJ",
			"display_first_last": "RJ Hunter",
			"rosterstatus": 1,
			"from_year": "2015",
			"to_year": "2016",
			"playercode": "rj_hunter",
			"team_id": 1610612738,
			"team_city": "Boston",
			"team_name": "Celtics",
			"team_abbreviation": "BOS",
			"team_code": "celtics",
			"games_played_flag": "Y"
		},
		{
			"person_id": 203996,
			"display_last_comma_first": "Inglis, Damien",
			"display_first_last": "Damien Inglis",
			"rosterstatus": 1,
			"from_year": "2014",
			"to_year": "2015",
			"playercode": "Damien_Inglis",
			"team_id": 1610612749,
			"team_city": "Milwaukee",
			"team_name": "Bucks",
			"team_abbreviation": "MIL",
			"team_code": "bucks",
			"games_played_flag": "Y"
		},
		{
			"person_id": 101127,
			"display_last_comma_first": "Jack, Jarrett",
			"display_first_last": "Jarrett Jack",
			"rosterstatus": 1,
			"from_year": "2005",
			"to_year": "2015",
			"playercode": "jarrett_jack",
			"team_id": 1610612751,
			"team_city": "Brooklyn",
			"team_name": "Nets",
			"team_abbreviation": "BKN",
			"team_code": "nets",
			"games_played_flag": "Y"
		},
		{
			"person_id": 202704,
			"display_last_comma_first": "Jackson, Reggie",
			"display_first_last": "Reggie Jackson",
			"rosterstatus": 1,
			"from_year": "2011",
			"to_year": "2016",
			"playercode": "Reggie_Jackson",
			"team_id": 1610612765,
			"team_city": "Detroit",
			"team_name": "Pistons",
			"team_abbreviation": "DET",
			"team_code": "pistons",
			"games_played_flag": "Y"
		},
		{
			"person_id": 203928,
			"display_last_comma_first": "Jefferson, Cory",
			"display_first_last": "Cory Jefferson",
			"rosterstatus": 0,
			"from_year": "2014",
			"to_year": "2015",
			"playercode": "cory_jefferson",
			"team_id": 0,
			"team_city": "",
			"team_name": "",
			"team_abbreviation": "",
			"team_code": "",
			"games_played_flag": "Y"
		},
		{
			"person_id": 203187,
			"display_last_comma_first": "Johnson, Chris",
			"display_first_last": "Chris Johnson",
			"rosterstatus": 1,
			"from_year": "2012",
			"to_year": "2015",
			"playercode": "christapher_johnson",
			"team_id": 1610612762,
			"team_city": "Utah",
			"team_name": "Jazz",
			"team_abbreviation": "UTA",
			"team_code": "jazz",
			"games_played_flag": "Y"
		},
		{
			"person_id": 203111,
			"display_last_comma_first": "Johnson, Orlando",
			"display_first_last": "Orlando Johnson",
			"rosterstatus": 0,
			"from_year": "2012",
			"to_year": "2015",
			"playercode": "orlando_johnson",
			"team_id": 0,
			"team_city": "",
			"team_name": "",
			"team_abbreviation": "",
			"team_code": "",
			"games_played_flag": "Y"
		},
		{
			"person_id": 2563,
			"display_last_comma_first": "Jones, Dahntay",
			"display_first_last": "Dahntay Jones",
			"rosterstatus": 1,
			"from_year": "2003",
			"to_year": "2015",
			"playercode": "Dahntay_Jones",
			"team_id": 1610612739,
			"team_city": "Cleveland",
			"team_name": "Cavaliers",
			"team_abbreviation": "CLE",
			"team_code": "cavaliers",
			"games_played_flag": "Y"
		},
		{
			"person_id": 2549,
			"display_last_comma_first": "Kaman, Chris",
			"display_first_last": "Chris Kaman",
			"rosterstatus": 1,
			"from_year": "2003",
			"to_year": "2015",
			"playercode": "chris_kaman",
			"team_id": 1610612757,
			"team_city": "Portland",
			"team_name": "Trail Blazers",
			"team_abbreviation": "POR",
			"team_code": "blazers",
			"games_played_flag": "Y"
		},
		{
			"person_id": 203508,
			"display_last_comma_first": "Karasev, Sergey",
			"display_first_last": "Sergey Karasev",
			"rosterstatus": 1,
			"from_year": "2013",
			"to_year": "2015",
			"playercode": "sergey_karasev",
			"team_id": 1610612751,
			"team_city": "Brooklyn",
			"team_name": "Nets",
			"team_abbreviation": "BKN",
			"team_code": "nets",
			"games_played_flag": "Y"
		},
		{
			"person_id": 201619,
			"display_last_comma_first": "Kaun, Sasha",
			"display_first_last": "Sasha Kaun",
			"rosterstatus": 1,
			"from_year": "2015",
			"to_year": "2015",
			"playercode": "sasha_kaun",
			"team_id": 1610612739,
			"team_city": "Cleveland",
			"team_name": "Cavaliers",
			"team_abbreviation": "CLE",
			"team_code": "cavaliers",
			"games_played_flag": "Y"
		},
		{
			"person_id": 201171,
			"display_last_comma_first": "Landry, Carl",
			"display_first_last": "Carl Landry",
			"rosterstatus": 1,
			"from_year": "2007",
			"to_year": "2015",
			"playercode": "carl_landry",
			"team_id": 1610612755,
			"team_city": "Philadelphia",
			"team_name": "76ers",
			"team_abbreviation": "PHI",
			"team_code": "sixers",
			"games_played_flag": "Y"
		},
		{
			"person_id": 203499,
			"display_last_comma_first": "Larkin, Shane",
			"display_first_last": "Shane Larkin",
			"rosterstatus": 1,
			"from_year": "2013",
			"to_year": "2015",
			"playercode": "shane_larkin",
			"team_id": 1610612751,
			"team_city": "Brooklyn",
			"team_name": "Nets",
			"team_abbreviation": "BKN",
			"team_code": "nets",
			"games_played_flag": "Y"
		},
		{
			"person_id": 101133,
			"display_last_comma_first": "Mahinmi, Ian",
			"display_first_last": "Ian Mahinmi",
			"rosterstatus": 1,
			"from_year": "2007",
			"to_year": "2016",
			"playercode": "Ian_Mahinmi",
			"team_id": 1610612754,
			"team_city": "Indiana",
			"team_name": "Pacers",
			"team_abbreviation": "IND",
			"team_code": "pacers",
			"games_played_flag": "Y"
		},
		{
			"person_id": 203906,
			"display_last_comma_first": "Marble, Devyn",
			"display_first_last": "Devyn Marble",
			"rosterstatus": 1,
			"from_year": "2014",
			"to_year": "2015",
			"playercode": "devyn_marble",
			"team_id": 1610612753,
			"team_city": "Orlando",
			"team_name": "Magic",
			"team_abbreviation": "ORL",
			"team_code": "magic",
			"games_played_flag": "Y"
		},
		{
			"person_id": 203088,
			"display_last_comma_first": "Marshall, Kendall",
			"display_first_last": "Kendall Marshall",
			"rosterstatus": 1,
			"from_year": "2012",
			"to_year": "2015",
			"playercode": "kendall_marshall",
			"team_id": 1610612755,
			"team_city": "Philadelphia",
			"team_name": "76ers",
			"team_abbreviation": "PHI",
			"team_code": "sixers",
			"games_played_flag": "Y"
		},
		{
			"person_id": 2755,
			"display_last_comma_first": "Martin, Kevin",
			"display_first_last": "Kevin Martin",
			"rosterstatus": 1,
			"from_year": "2004",
			"to_year": "2015",
			"playercode": "kevin_martin",
			"team_id": 1610612759,
			"team_city": "San Antonio",
			"team_name": "Spurs",
			"team_abbreviation": "SAS",
			"team_code": "spurs",
			"games_played_flag": "Y"
		},
		{
			"person_id": 201564,
			"display_last_comma_first": "Mayo, O.J.",
			"display_first_last": "O.J. Mayo",
			"rosterstatus": 1,
			"from_year": "2008",
			"to_year": "2015",
			"playercode": "oj_mayo",
			"team_id": 1610612749,
			"team_city": "Milwaukee",
			"team_name": "Bucks",
			"team_abbreviation": "MIL",
			"team_code": "bucks",
			"games_played_flag": "Y"
		},
		{
			"person_id": 203492,
			"display_last_comma_first": "McCallum, Ray",
			"display_first_last": "Ray McCallum",
			"rosterstatus": 0,
			"from_year": "2013",
			"to_year": "2015",
			"playercode": "Ray_McCallum",
			"team_id": 0,
			"team_city": "",
			"team_name": "",
			"team_abbreviation": "",
			"team_code": "",
			"games_played_flag": "Y"
		},
		{
			"person_id": 203956,
			"display_last_comma_first": "McGary, Mitch",
			"display_first_last": "Mitch McGary",
			"rosterstatus": 1,
			"from_year": "2014",
			"to_year": "2015",
			"playercode": "Mitch_McGary",
			"team_id": 1610612760,
			"team_city": "Oklahoma City",
			"team_name": "Thunder",
			"team_abbreviation": "OKC",
			"team_code": "thunder",
			"games_played_flag": "Y"
		},
		{
			"person_id": 201975,
			"display_last_comma_first": "Meeks, Jodie",
			"display_first_last": "Jodie Meeks",
			"rosterstatus": 1,
			"from_year": "2009",
			"to_year": "2016",
			"playercode": "Jodie_Meeks",
			"team_id": 1610612765,
			"team_city": "Detroit",
			"team_name": "Pistons",
			"team_abbreviation": "DET",
			"team_code": "pistons",
			"games_played_flag": "Y"
		},
		{
			"person_id": 203114,
			"display_last_comma_first": "Middleton, Khris",
			"display_first_last": "Khris Middleton",
			"rosterstatus": 1,
			"from_year": "2012",
			"to_year": "2016",
			"playercode": "Khris_Middleton",
			"team_id": 1610612749,
			"team_city": "Milwaukee",
			"team_name": "Bucks",
			"team_abbreviation": "MIL",
			"team_code": "bucks",
			"games_played_flag": "Y"
		},
		{
			"person_id": 1889,
			"display_last_comma_first": "Miller, Andre",
			"display_first_last": "Andre Miller",
			"rosterstatus": 1,
			"from_year": "1999",
			"to_year": "2015",
			"playercode": "andre_miller",
			"team_id": 1610612759,
			"team_city": "San Antonio",
			"team_name": "Spurs",
			"team_abbreviation": "SAS",
			"team_code": "spurs",
			"games_played_flag": "Y"
		},
		{
			"person_id": 202407,
			"display_last_comma_first": "Millsap, Elijah",
			"display_first_last": "Elijah Millsap",
			"rosterstatus": 0,
			"from_year": "2014",
			"to_year": "2015",
			"playercode": "elijah_millsap",
			"team_id": 0,
			"team_city": "",
			"team_name": "",
			"team_abbreviation": "",
			"team_code": "",
			"games_played_flag": "Y"
		},
		{
			"person_id": 1737,
			"display_last_comma_first": "Mohammed, Nazr",
			"display_first_last": "Nazr Mohammed",
			"rosterstatus": 1,
			"from_year": "1998",
			"to_year": "2015",
			"playercode": "nazr_mohammed",
			"team_id": 1610612760,
			"team_city": "Oklahoma City",
			"team_name": "Thunder",
			"team_abbreviation": "OKC",
			"team_code": "thunder",
			"games_played_flag": "Y"
		},
		{
			"person_id": 1626242,
			"display_last_comma_first": "Montero, Luis",
			"display_first_last": "Luis Montero",
			"rosterstatus": 1,
			"from_year": "2015",
			"to_year": "2015",
			"playercode": "Luis_Montero",
			"team_id": 1610612757,
			"team_city": "Portland",
			"team_name": "Trail Blazers",
			"team_abbreviation": "POR",
			"team_code": "blazers",
			"games_played_flag": "Y"
		},
		{
			"person_id": 203961,
			"display_last_comma_first": "Moreland, Eric",
			"display_first_last": "Eric Moreland",
			"rosterstatus": 1,
			"from_year": "2014",
			"to_year": "2015",
			"playercode": "eric_moreland",
			"team_id": 1610612758,
			"team_city": "Sacramento",
			"team_name": "Kings",
			"team_abbreviation": "SAC",
			"team_code": "kings",
			"games_played_flag": "Y"
		},
		{
			"person_id": 202700,
			"display_last_comma_first": "Motiejunas, Donatas",
			"display_first_last": "Donatas Motiejunas",
			"rosterstatus": 1,
			"from_year": "2012",
			"to_year": "2015",
			"playercode": "donatas_motiejunas",
			"team_id": 1610612745,
			"team_city": "Houston",
			"team_name": "Rockets",
			"team_abbreviation": "HOU",
			"team_code": "rockets",
			"games_played_flag": "Y"
		},
		{
			"person_id": 204098,
			"display_last_comma_first": "Munford, Xavier",
			"display_first_last": "Xavier Munford",
			"rosterstatus": 1,
			"from_year": "2015",
			"to_year": "2015",
			"playercode": "xavier_munford",
			"team_id": 1610612763,
			"team_city": "Memphis",
			"team_name": "Grizzlies",
			"team_abbreviation": "MEM",
			"team_code": "grizzlies",
			"games_played_flag": "Y"
		},
		{
			"person_id": 202390,
			"display_last_comma_first": "Neal, Gary",
			"display_first_last": "Gary Neal",
			"rosterstatus": 0,
			"from_year": "2010",
			"to_year": "2015",
			"playercode": "gary_neal",
			"team_id": 0,
			"team_city": "",
			"team_name": "",
			"team_abbreviation": "",
			"team_code": "",
			"games_played_flag": "Y"
		},
		{
			"person_id": 203457,
			"display_last_comma_first": "Noel, Nerlens",
			"display_first_last": "Nerlens Noel",
			"rosterstatus": 1,
			"from_year": "2013",
			"to_year": "2016",
			"playercode": "Nerlens_Noel",
			"team_id": 1610612755,
			"team_city": "Philadelphia",
			"team_name": "76ers",
			"team_abbreviation": "PHI",
			"team_code": "sixers",
			"games_played_flag": "Y"
		},
		{
			"person_id": 1626266,
			"display_last_comma_first": "O'Brien, JJ",
			"display_first_last": "JJ O'Brien",
			"rosterstatus": 0,
			"from_year": "2015",
			"to_year": "2015",
			"playercode": "JJ_O'Brien",
			"team_id": 0,
			"team_city": "",
			"team_name": "",
			"team_abbreviation": "",
			"team_code": "",
			"games_played_flag": "Y"
		},
		{
			"person_id": 203948,
			"display_last_comma_first": "O'Bryant III, Johnny",
			"display_first_last": "Johnny O'Bryant III",
			"rosterstatus": 1,
			"from_year": "2014",
			"to_year": "2015",
			"playercode": "johnny_o'bryant iii",
			"team_id": 1610612749,
			"team_city": "Milwaukee",
			"team_name": "Bucks",
			"team_abbreviation": "MIL",
			"team_code": "bucks",
			"games_played_flag": "Y"
		},
		{
			"person_id": 203123,
			"display_last_comma_first": "Papanikolaou, Kostas",
			"display_first_last": "Kostas Papanikolaou",
			"rosterstatus": 0,
			"from_year": "2014",
			"to_year": "2015",
			"playercode": "kostas_papanikolaou",
			"team_id": 0,
			"team_city": "",
			"team_name": "",
			"team_abbreviation": "",
			"team_code": "",
			"games_played_flag": "Y"
		},
		{
			"person_id": 203934,
			"display_last_comma_first": "Patterson, Lamar",
			"display_first_last": "Lamar Patterson",
			"rosterstatus": 1,
			"from_year": "2015",
			"to_year": "2015",
			"playercode": "Lamar_Patterson",
			"team_id": 1610612737,
			"team_city": "Atlanta",
			"team_name": "Hawks",
			"team_abbreviation": "ATL",
			"team_code": "hawks",
			"games_played_flag": "Y"
		},
		{
			"person_id": 1626166,
			"display_last_comma_first": "Payne, Cameron",
			"display_first_last": "Cameron Payne",
			"rosterstatus": 1,
			"from_year": "2015",
			"to_year": "2016",
			"playercode": "Cameron_Payne",
			"team_id": 1610612760,
			"team_city": "Oklahoma City",
			"team_name": "Thunder",
			"team_abbreviation": "OKC",
			"team_code": "thunder",
			"games_played_flag": "Y"
		},
		{
			"person_id": 201593,
			"display_last_comma_first": "Pekovic, Nikola",
			"display_first_last": "Nikola Pekovic",
			"rosterstatus": 1,
			"from_year": "2010",
			"to_year": "2016",
			"playercode": "nikola_pekovic",
			"team_id": 1610612750,
			"team_city": "Minnesota",
			"team_name": "Timberwolves",
			"team_abbreviation": "MIN",
			"team_code": "timberwolves",
			"games_played_flag": "Y"
		},
		{
			"person_id": 2570,
			"display_last_comma_first": "Perkins, Kendrick",
			"display_first_last": "Kendrick Perkins",
			"rosterstatus": 1,
			"from_year": "2003",
			"to_year": "2015",
			"playercode": "kendrick_perkins",
			"team_id": 1610612740,
			"team_city": "New Orleans",
			"team_name": "Pelicans",
			"team_abbreviation": "NOP",
			"team_code": "pelicans",
			"games_played_flag": "Y"
		},
		{
			"person_id": 1718,
			"display_last_comma_first": "Pierce, Paul",
			"display_first_last": "Paul Pierce",
			"rosterstatus": 1,
			"from_year": "1998",
			"to_year": "2016",
			"playercode": "paul_pierce",
			"team_id": 1610612746,
			"team_city": "LA",
			"team_name": "Clippers",
			"team_abbreviation": "LAC",
			"team_code": "clippers",
			"games_played_flag": "Y"
		},
		{
			"person_id": 202353,
			"display_last_comma_first": "Pleiss, Tibor",
			"display_first_last": "Tibor Pleiss",
			"rosterstatus": 1,
			"from_year": "2015",
			"to_year": "2015",
			"playercode": "tibor_pleiss",
			"team_id": 1610612762,
			"team_city": "Utah",
			"team_name": "Jazz",
			"team_abbreviation": "UTA",
			"team_code": "jazz",
			"games_played_flag": "Y"
		},
		{
			"person_id": 203515,
			"display_last_comma_first": "Pressey, Phil",
			"display_first_last": "Phil Pressey",
			"rosterstatus": 0,
			"from_year": "2013",
			"to_year": "2015",
			"playercode": "Phil_Pressey",
			"team_id": 0,
			"team_city": "",
			"team_name": "",
			"team_abbreviation": "",
			"team_code": "",
			"games_played_flag": "Y"
		},
		{
			"person_id": 101179,
			"display_last_comma_first": "Price, Ronnie",
			"display_first_last": "Ronnie Price",
			"rosterstatus": 1,
			"from_year": "2005",
			"to_year": "2015",
			"playercode": "Ronnie_Price",
			"team_id": 1610612756,
			"team_city": "Phoenix",
			"team_name": "Suns",
			"team_abbreviation": "PHX",
			"team_code": "suns",
			"games_played_flag": "Y"
		},
		{
			"person_id": 203143,
			"display_last_comma_first": "Prigioni, Pablo",
			"display_first_last": "Pablo Prigioni",
			"rosterstatus": 1,
			"from_year": "2012",
			"to_year": "2015",
			"playercode": "Pablo_Prigioni",
			"team_id": 1610612746,
			"team_city": "LA",
			"team_name": "Clippers",
			"team_abbreviation": "LAC",
			"team_code": "clippers",
			"games_played_flag": "Y"
		},
		{
			"person_id": 2419,
			"display_last_comma_first": "Prince, Tayshaun",
			"display_first_last": "Tayshaun Prince",
			"rosterstatus": 1,
			"from_year": "2002",
			"to_year": "2015",
			"playercode": "tayshaun_prince",
			"team_id": 1610612750,
			"team_city": "Minnesota",
			"team_name": "Timberwolves",
			"team_abbreviation": "MIN",
			"team_code": "timberwolves",
			"games_played_flag": "Y"
		},
		{
			"person_id": 101126,
			"display_last_comma_first": "Robinson, Nate",
			"display_first_last": "Nate Robinson",
			"rosterstatus": 0,
			"from_year": "2005",
			"to_year": "2015",
			"playercode": "nate_robinson",
			"team_id": 0,
			"team_city": "",
			"team_name": "",
			"team_abbreviation": "",
			"team_code": "",
			"games_played_flag": "Y"
		},
		{
			"person_id": 203135,
			"display_last_comma_first": "Sacre, Robert",
			"display_first_last": "Robert Sacre",
			"rosterstatus": 1,
			"from_year": "2012",
			"to_year": "2015",
			"playercode": "robert_sacre",
			"team_id": 1610612747,
			"team_city": "Los Angeles",
			"team_name": "Lakers",
			"team_abbreviation": "LAL",
			"team_code": "lakers",
			"games_played_flag": "Y"
		},
		{
			"person_id": 203960,
			"display_last_comma_first": "Sampson, JaKarr",
			"display_first_last": "JaKarr Sampson",
			"rosterstatus": 1,
			"from_year": "2014",
			"to_year": "2015",
			"playercode": "jakarr_sampson",
			"team_id": 1610612743,
			"team_city": "Denver",
			"team_name": "Nuggets",
			"team_abbreviation": "DEN",
			"team_code": "nuggets",
			"games_played_flag": "Y"
		},
		{
			"person_id": 203118,
			"display_last_comma_first": "Scott, Mike",
			"display_first_last": "Mike Scott",
			"rosterstatus": 1,
			"from_year": "2012",
			"to_year": "2016",
			"playercode": "Mike_Scott",
			"team_id": 1610612737,
			"team_city": "Atlanta",
			"team_name": "Hawks",
			"team_abbreviation": "ATL",
			"team_code": "hawks",
			"games_played_flag": "Y"
		},
		{
			"person_id": 203156,
			"display_last_comma_first": "Sims, Henry",
			"display_first_last": "Henry Sims",
			"rosterstatus": 1,
			"from_year": "2012",
			"to_year": "2015",
			"playercode": "Henry_Sims",
			"team_id": 1610612751,
			"team_city": "Brooklyn",
			"team_name": "Nets",
			"team_abbreviation": "BKN",
			"team_code": "nets",
			"games_played_flag": "Y"
		},
		{
			"person_id": 202388,
			"display_last_comma_first": "Sloan, Donald",
			"display_first_last": "Donald Sloan",
			"rosterstatus": 1,
			"from_year": "2011",
			"to_year": "2015",
			"playercode": "donald_sloan",
			"team_id": 1610612751,
			"team_city": "Brooklyn",
			"team_name": "Nets",
			"team_abbreviation": "BKN",
			"team_code": "nets",
			"games_played_flag": "Y"
		},
		{
			"person_id": 202962,
			"display_last_comma_first": "Smith, Greg",
			"display_first_last": "Greg Smith",
			"rosterstatus": 1,
			"from_year": "2011",
			"to_year": "2015",
			"playercode": "greg_smith",
			"team_id": 1610612750,
			"team_city": "Minnesota",
			"team_name": "Timberwolves",
			"team_abbreviation": "MIN",
			"team_code": "timberwolves",
			"games_played_flag": "Y"
		},
		{
			"person_id": 2746,
			"display_last_comma_first": "Smith, Josh",
			"display_first_last": "Josh Smith",
			"rosterstatus": 1,
			"from_year": "2004",
			"to_year": "2015",
			"playercode": "josh_smith",
			"team_id": 1610612745,
			"team_city": "Houston",
			"team_name": "Rockets",
			"team_abbreviation": "HOU",
			"team_code": "rockets",
			"games_played_flag": "Y"
		},
		{
			"person_id": 203893,
			"display_last_comma_first": "Smith, Russ",
			"display_first_last": "Russ Smith",
			"rosterstatus": 0,
			"from_year": "2014",
			"to_year": "2015",
			"playercode": "russ_smith",
			"team_id": 0,
			"team_city": "",
			"team_name": "",
			"team_abbreviation": "",
			"team_code": "",
			"games_played_flag": "Y"
		},
		{
			"person_id": 201168,
			"display_last_comma_first": "Splitter, Tiago",
			"display_first_last": "Tiago Splitter",
			"rosterstatus": 1,
			"from_year": "2010",
			"to_year": "2016",
			"playercode": "Tiago_Splitter",
			"team_id": 1610612737,
			"team_city": "Atlanta",
			"team_name": "Hawks",
			"team_abbreviation": "ATL",
			"team_code": "hawks",
			"games_played_flag": "Y"
		},
		{
			"person_id": 202362,
			"display_last_comma_first": "Stephenson, Lance",
			"display_first_last": "Lance Stephenson",
			"rosterstatus": 1,
			"from_year": "2010",
			"to_year": "2016",
			"playercode": "lance_stephenson",
			"team_id": 1610612763,
			"team_city": "Memphis",
			"team_name": "Grizzlies",
			"team_abbreviation": "MEM",
			"team_code": "grizzlies",
			"games_played_flag": "Y"
		},
		{
			"person_id": 1627293,
			"display_last_comma_first": "Stepheson, Alex",
			"display_first_last": "Alex Stepheson",
			"rosterstatus": 0,
			"from_year": "2015",
			"to_year": "2015",
			"playercode": "alex_stepheson",
			"team_id": 0,
			"team_city": "",
			"team_name": "",
			"team_abbreviation": "",
			"team_code": "",
			"games_played_flag": "Y"
		},
		{
			"person_id": 2405,
			"display_last_comma_first": "Stoudemire, Amar'e",
			"display_first_last": "Amar'e Stoudemire",
			"rosterstatus": 1,
			"from_year": "2002",
			"to_year": "2015",
			"playercode": "amare_stoudemire",
			"team_id": 1610612748,
			"team_city": "Miami",
			"team_name": "Heat",
			"team_abbreviation": "MIA",
			"team_code": "heat",
			"games_played_flag": "Y"
		},
		{
			"person_id": 203096,
			"display_last_comma_first": "Sullinger, Jared",
			"display_first_last": "Jared Sullinger",
			"rosterstatus": 1,
			"from_year": "2012",
			"to_year": "2016",
			"playercode": "Jared_Sullinger",
			"team_id": 1610612738,
			"team_city": "Boston",
			"team_name": "Celtics",
			"team_abbreviation": "BOS",
			"team_code": "celtics",
			"games_played_flag": "Y"
		},
		{
			"person_id": 204002,
			"display_last_comma_first": "Tavares, Edy",
			"display_first_last": "Edy Tavares",
			"rosterstatus": 1,
			"from_year": "2015",
			"to_year": "2016",
			"playercode": "edy_tavares",
			"team_id": 1610612737,
			"team_city": "Atlanta",
			"team_name": "Hawks",
			"team_abbreviation": "ATL",
			"team_code": "hawks",
			"games_played_flag": "Y"
		},
		{
			"person_id": 201574,
			"display_last_comma_first": "Thompson, Jason",
			"display_first_last": "Jason Thompson",
			"rosterstatus": 1,
			"from_year": "2008",
			"to_year": "2015",
			"playercode": "jason_thompson",
			"team_id": 1610612761,
			"team_city": "Toronto",
			"team_name": "Raptors",
			"team_abbreviation": "TOR",
			"team_code": "raptors",
			"games_played_flag": "Y"
		},
		{
			"person_id": 1626253,
			"display_last_comma_first": "Toupane, Axel",
			"display_first_last": "Axel Toupane",
			"rosterstatus": 1,
			"from_year": "2015",
			"to_year": "2015",
			"playercode": "Axel_Toupane",
			"team_id": 1610612743,
			"team_city": "Denver",
			"team_name": "Nuggets",
			"team_abbreviation": "DEN",
			"team_code": "nuggets",
			"games_played_flag": "Y"
		},
		{
			"person_id": 202349,
			"display_last_comma_first": "Vasquez, Greivis",
			"display_first_last": "Greivis Vasquez",
			"rosterstatus": 1,
			"from_year": "2010",
			"to_year": "2016",
			"playercode": "greivis_vasquez",
			"team_id": 1610612749,
			"team_city": "Milwaukee",
			"team_name": "Bucks",
			"team_abbreviation": "MIL",
			"team_code": "bucks",
			"games_played_flag": "Y"
		},
		{
			"person_id": 101111,
			"display_last_comma_first": "Villanueva, Charlie",
			"display_first_last": "Charlie Villanueva",
			"rosterstatus": 1,
			"from_year": "2005",
			"to_year": "2015",
			"playercode": "charlie_villanueva",
			"team_id": 1610612742,
			"team_city": "Dallas",
			"team_name": "Mavericks",
			"team_abbreviation": "DAL",
			"team_code": "mavericks",
			"games_played_flag": "Y"
		},
		{
			"person_id": 1627362,
			"display_last_comma_first": "Weber, Briante",
			"display_first_last": "Briante Weber",
			"rosterstatus": 1,
			"from_year": "2015",
			"to_year": "2015",
			"playercode": "Briante_Weber",
			"team_id": 1610612748,
			"team_city": "Miami",
			"team_name": "Heat",
			"team_abbreviation": "MIA",
			"team_code": "heat",
			"games_played_flag": "Y"
		},
		{
			"person_id": 201603,
			"display_last_comma_first": "Weems, Sonny",
			"display_first_last": "Sonny Weems",
			"rosterstatus": 0,
			"from_year": "2008",
			"to_year": "2015",
			"playercode": "sonny_weems",
			"team_id": 0,
			"team_city": "",
			"team_name": "",
			"team_abbreviation": "",
			"team_code": "",
			"games_played_flag": "Y"
		},
		{
			"person_id": 203963,
			"display_last_comma_first": "Whittington, Shayne",
			"display_first_last": "Shayne Whittington",
			"rosterstatus": 1,
			"from_year": "2014",
			"to_year": "2015",
			"playercode": "shayne_whittington",
			"team_id": 1610612754,
			"team_city": "Indiana",
			"team_name": "Pacers",
			"team_abbreviation": "IND",
			"team_code": "pacers",
			"games_played_flag": "Y"
		},
		{
			"person_id": 202343,
			"display_last_comma_first": "Williams, Elliot",
			"display_first_last": "Elliot Williams",
			"rosterstatus": 0,
			"from_year": "2010",
			"to_year": "2015",
			"playercode": "elliot_williams",
			"team_id": 0,
			"team_city": "",
			"team_name": "",
			"team_abbreviation": "",
			"team_code": "",
			"games_played_flag": "Y"
		},
		{
			"person_id": 2590,
			"display_last_comma_first": "Williams, Mo",
			"display_first_last": "Mo Williams",
			"rosterstatus": 1,
			"from_year": "2003",
			"to_year": "2016",
			"playercode": "Mo_Williams",
			"team_id": 1610612739,
			"team_city": "Cleveland",
			"team_name": "Cavaliers",
			"team_abbreviation": "CLE",
			"team_code": "cavaliers",
			"games_played_flag": "Y"
		},
		{
			"person_id": 201148,
			"display_last_comma_first": "Wright, Brandan",
			"display_first_last": "Brandan Wright",
			"rosterstatus": 1,
			"from_year": "2007",
			"to_year": "2016",
			"playercode": "Brandan_Wright",
			"team_id": 1610612763,
			"team_city": "Memphis",
			"team_name": "Grizzlies",
			"team_abbreviation": "MEM",
			"team_code": "grizzlies",
			"games_played_flag": "Y"
		},
		{
			"person_id": 1626153,
			"display_last_comma_first": "Wright, Delon",
			"display_first_last": "Delon Wright",
			"rosterstatus": 1,
			"from_year": "2015",
			"to_year": "2016",
			"playercode": "Delon_Wright",
			"team_id": 1610612761,
			"team_city": "Toronto",
			"team_name": "Raptors",
			"team_abbreviation": "TOR",
			"team_code": "raptors",
			"games_played_flag": "Y"
		},
		{
			"person_id": 2748,
			"display_last_comma_first": "Wright, Dorell",
			"display_first_last": "Dorell Wright",
			"rosterstatus": 1,
			"from_year": "2004",
			"to_year": "2015",
			"playercode": "dorell_wright",
			"team_id": 1610612748,
			"team_city": "Miami",
			"team_name": "Heat",
			"team_abbreviation": "MIA",
			"team_code": "heat",
			"games_played_flag": "Y"
		},
		{
			"person_id": 203100,
			"display_last_comma_first": "Wroten, Tony",
			"display_first_last": "Tony Wroten",
			"rosterstatus": 1,
			"from_year": "2012",
			"to_year": "2015",
			"playercode": "tony_wroten",
			"team_id": 1610612752,
			"team_city": "New York",
			"team_name": "Knicks",
			"team_abbreviation": "NYK",
			"team_code": "knicks",
			"games_played_flag": "Y"
		}
	]
}